[
  {"step_number":1,"name_en":"Raw Material Receiving","name_cn":"原材料接收检验","weight":4,"category":"fab_fixed","hours_fixed":2.0,"hours_variable":"","spool_type":"ALL","display_order":1,"is_conditional":0,"is_hold_point":0,"is_release":0,"phase":"fab"},
  {"step_number":2,"name_en":"Material Identification & Traceability","name_cn":"材料标识及可追溯性","weight":4,"category":"fab_fixed","hours_fixed":2.0,"hours_variable":"","spool_type":"ALL","display_order":2,"is_conditional":0,"is_hold_point":0,"is_release":0,"phase":"fab"},
  {"step_number":3,"name_en":"Pipe Cutting as per Spool Drawings","name_cn":"按管段图切割管道","weight":7,"category":"fab_fixed","hours_fixed":2.0,"hours_variable":"","spool_type":"ALL","display_order":3,"is_conditional":0,"is_hold_point":0,"is_release":0,"phase":"fab"},
  {"step_number":4,"name_en":"End Preparation / Beveling","name_cn":"管口准备 / 坡口加工","weight":5,"category":"fab_fixed","hours_fixed":2.0,"hours_variable":"","spool_type":"ALL","display_order":4,"is_conditional":0,"is_hold_point":0,"is_release":0,"phase":"fab"},
  {"step_number":5,"name_en":"Fit-up & Assembly","name_cn":"组对及装配检验","weight":8,"category":"fab_fixed","hours_fixed":2.0,"hours_variable":"","spool_type":"ALL","display_order":5,"is_conditional":0,"is_hold_point":0,"is_release":0,"phase":"fab"},
  {"step_number":16,"name_en":"Branch Welding","name_cn":"支管焊接","weight":5,"category":"branch","hours_fixed":2.0,"hours_variable":"","spool_type":"ALL","display_order":6,"is_conditional":1,"is_hold_point":0,"is_release":0,"phase":"fab"},
  {"step_number":6,"name_en":"Production Welding GTAW/SAW","name_cn":"GTAW/SAW生产焊接","weight":10,"category":"welding","hours_fixed":0,"hours_variable":"welding","spool_type":"ALL","display_order":7,"is_conditional":0,"is_hold_point":0,"is_release":0,"phase":"fab"},
  {"step_number":7,"name_en":"Visual Testing (VT) — 100%","name_cn":"目视检验VT（全检）","weight":5,"category":"fab_fixed","hours_fixed":2.0,"hours_variable":"","spool_type":"ALL","display_order":8,"is_conditional":0,"is_hold_point":0,"is_release":0,"phase":"fab"},
  {"step_number":8,"name_en":"Radiographic Testing (RT) — 100%","name_cn":"射线检测RT（全检）★停止点","weight":8,"category":"fab_fixed","hours_fixed":2.0,"hours_variable":"","spool_type":"ALL","display_order":9,"is_conditional":0,"is_hold_point":1,"is_release":0,"phase":"fab"},
  {"step_number":9,"name_en":"Liquid Penetrant Testing (PT) — 100%","name_cn":"液体渗透检测PT（全检）","weight":5,"category":"fab_fixed","hours_fixed":2.0,"hours_variable":"","spool_type":"ALL","display_order":10,"is_conditional":0,"is_hold_point":0,"is_release":0,"phase":"fab"},
  {"step_number":10,"name_en":"PMI on Finished Spools","name_cn":"成品管段PMI检测","weight":4,"category":"fab_fixed","hours_fixed":2.0,"hours_variable":"","spool_type":"ALL","display_order":11,"is_conditional":0,"is_hold_point":0,"is_release":0,"phase":"fab"},
  {"step_number":11,"name_en":"Ferrite Content Measurement","name_cn":"铁素体含量测量","weight":4,"category":"fab_fixed","hours_fixed":2.0,"hours_variable":"","spool_type":"ALL","display_order":12,"is_conditional":0,"is_hold_point":0,"is_release":0,"phase":"fab"},
  {"step_number":12,"name_en":"Weld Identification & Stamping","name_cn":"焊缝标识及钢印","weight":3,"category":"fab_fixed","hours_fixed":2.0,"hours_variable":"","spool_type":"ALL","display_order":13,"is_conditional":0,"is_hold_point":0,"is_release":0,"phase":"fab"},
  {"step_number":13,"name_en":"Dimensional Inspection Final","name_cn":"最终尺寸检验","weight":5,"category":"fab_fixed","hours_fixed":2.0,"hours_variable":"","spool_type":"ALL","display_order":14,"is_conditional":0,"is_hold_point":0,"is_release":0,"phase":"fab"},
  {"step_number":14,"name_en":"Cleaning Pre-Pickling","name_cn":"酸洗前清洁","weight":3,"category":"fab_fixed","hours_fixed":2.0,"hours_variable":"","spool_type":"ALL","display_order":15,"is_conditional":0,"is_hold_point":0,"is_release":0,"phase":"fab"},
  {"step_number":15,"name_en":"Pickling & Passivation","name_cn":"酸洗钝化","weight":8,"category":"fab_fixed","hours_fixed":2.0,"hours_variable":"","spool_type":"ALL","display_order":16,"is_conditional":0,"is_hold_point":0,"is_release":0,"phase":"fab"},
  {"step_number":17,"name_en":"Post-Passivation Inspection Ferroxyl","name_cn":"钝化后铁离子检测","weight":5,"category":"fab_fixed","hours_fixed":2.0,"hours_variable":"","spool_type":"ALL","display_order":17,"is_conditional":0,"is_hold_point":0,"is_release":0,"phase":"fab"},
  {"step_number":18,"name_en":"Final Marking & Identification","name_cn":"最终标识及标记","weight":4,"category":"fab_fixed","hours_fixed":2.0,"hours_variable":"","spool_type":"ALL","display_order":18,"is_conditional":0,"is_hold_point":0,"is_release":0,"phase":"fab"},
  {"step_number":19,"name_en":"Packing & Dispatch","name_cn":"包装及发运","weight":3,"category":"packing","hours_fixed":3.0,"hours_variable":"","spool_type":"ALL","display_order":19,"is_conditional":0,"is_hold_point":0,"is_release":1,"phase":"fab"}
]
